wechaty_puppet/__init__.py
wechaty_puppet/config.py
wechaty_puppet/exceptions.py
wechaty_puppet/logger.py
wechaty_puppet/puppet.py
wechaty_puppet/state_switch.py
wechaty_puppet/version.py
wechaty_puppet/watch_dog.py
wechaty_puppet/file_box/__init__.py
wechaty_puppet/file_box/file_box.py
wechaty_puppet/file_box/type.py
wechaty_puppet/file_box/utils.py
wechaty_puppet/filter/__init__.py
wechaty_puppet/filter/filed.py
wechaty_puppet/memory_card/__init__.py
wechaty_puppet/memory_card/memory_card.py
wechaty_puppet/schemas/__init__.py
wechaty_puppet/schemas/base.py
wechaty_puppet/schemas/contact.py
wechaty_puppet/schemas/event.py
wechaty_puppet/schemas/friendship.py
wechaty_puppet/schemas/message.py
wechaty_puppet/schemas/mini_program.py
wechaty_puppet/schemas/puppet.py
wechaty_puppet/schemas/room.py
wechaty_puppet/schemas/types.py
wechaty_puppet/schemas/url_link.py
wechaty_puppet-0.4.23.dist-info/LICENSE
wechaty_puppet-0.4.23.dist-info/METADATA
wechaty_puppet-0.4.23.dist-info/WHEEL
wechaty_puppet-0.4.23.dist-info/top_level.txt
wechaty_puppet-0.4.23.dist-info/RECORD
