Metadata-Version: 2.1
Name: wechaty-puppet
Version: 0.4.23
Summary: Abstract(Base) Class of Puppet Providers for Wechaty Framework
Home-page: https://github.com/wechaty/python-wechaty-puppet
Author: Huan LI (李卓桓)
Author-email: zixia@zixia.net
License: Apache-2.0
Platform: UNKNOWN
Classifier: Programming Language :: Python :: 3.7
Classifier: License :: OSI Approved :: Apache Software License
Classifier: Operating System :: OS Independent
Requires-Dist: pyee
Requires-Dist: requests
Requires-Dist: qrcode
